{
    "configurations": [
        {
            "name": "Linux",
            "includePath": [
                "${workspaceFolder}/**",
                "/usr/include/eigen3"
            ],
            "defines": [],
            "compilerPath": "/usr/bin/gcc",
            "cStandard": "gnu17",
            "cppStandard": "gnu++17",
            "intelliSenseMode": "linux-gcc-x64"
        },
        {
            "name": "Mac",
            "includePath": [
                "${workspaceFolder}/**",
                "/usr/local/include/",
                "/opt/homebrew/include/",
                "/opt/homebrew/include/eigen3",
                "/opt/local/include/"
            ],
            "defines": [],
            "macFrameworkPath": [
                "/Library/Developer/CommandLineTools/SDKs/MacOSX.sdk/System/Library/Frameworks"
            ],
            "compilerPath": "/usr/bin/clang",
            "cStandard": "c17",
            "cppStandard": "c++17",
            "intelliSenseMode": "macos-clang-arm64"
        }
    ],
    "version": 4
}